ssc/__init__.py
ssc/_ffi.py
ssc/api.py
ssc/core.py
ssc/ffibuilder.py
ssc/sscapi.h
ssc/modules/__init__.py
ssc/modules/battwatts.py
ssc/modules/pvwatts.py
sscpy-0.2.1.dist-info/LICENSE
sscpy-0.2.1.dist-info/METADATA
sscpy-0.2.1.dist-info/WHEEL
sscpy-0.2.1.dist-info/top_level.txt
sscpy-0.2.1.dist-info/RECORD
