Metadata-Version: 2.1
Name: sscpy
Version: 0.2.1
Summary: Python bindings for SAM Simulation Core (SSC)
Home-page: https://github.com/StationA/sscpy
Author: Station A
Author-email: software@stationa.com
License: License :: OSI Approved :: MIT License
Platform: UNKNOWN
Requires-Dist: cffi (>=1.0.0)
